semanticshare/__init__.py
semanticshare/io/__init__.py
semanticshare/io/odysz/__init__.py
semanticshare/io/odysz/semantics.py
semanticshare/io/odysz/semantic/__init__.py
semanticshare/io/odysz/semantic/jprotocol.py
semanticshare/io/odysz/semantic/jsession.py
semanticshare/io/odysz/semantic/jserv/__init__.py
semanticshare/io/odysz/semantic/jserv/echo.py
semanticshare/io/odysz/semantic/jserv/signup.py
semanticshare/io/oz/__init__.py
semanticshare/io/oz/invoke.py
semanticshare/io/oz/edge/__init__.py
semanticshare/io/oz/jserv/__init__.py
semanticshare/io/oz/jserv/docs/__init__.py
semanticshare/io/oz/jserv/docs/syn/__init__.py
semanticshare/io/oz/jserv/docs/syn/singleton.py
semanticshare/io/oz/register/central.py
semanticshare/io/oz/srv/__init__.py
semanticshare/io/oz/syn/__init__.py
semanticshare/io/oz/syn/registry.py
semanticshare/io/oz/syntier/__init__.py
semanticshare/io/oz/syntier/serv.py
semantics_py3-0.5.2.dist-info/METADATA
semantics_py3-0.5.2.dist-info/WHEEL
semantics_py3-0.5.2.dist-info/RECORD
